Metadata-Version: 2.1
Name: basic-statistic-distributions
Version: 0.3
Summary: Bionomial and Gaussion destributions
Home-page: https://github.com/huwwp/cryptocli
Author: Usman Naeem
Author-email: usmaanbinnaeem@gmail.com
License: Copyright 2021 usmanbinnaeem
Keywords: Gaussian or Binomial distributions
Platform: UNKNOWN
